pymc_experimental/__init__.py
pymc_experimental/linearmodel.py
pymc_experimental/model_builder.py
pymc_experimental/printing.py
pymc_experimental/version.py
pymc_experimental/version.txt
pymc_experimental/distributions/__init__.py
pymc_experimental/distributions/continuous.py
pymc_experimental/distributions/discrete.py
pymc_experimental/distributions/histogram_utils.py
pymc_experimental/distributions/timeseries.py
pymc_experimental/distributions/multivariate/__init__.py
pymc_experimental/distributions/multivariate/r2d2m2cp.py
pymc_experimental/gp/__init__.py
pymc_experimental/gp/latent_approx.py
pymc_experimental/inference/__init__.py
pymc_experimental/inference/find_map.py
pymc_experimental/inference/fit.py
pymc_experimental/inference/laplace.py
pymc_experimental/inference/pathfinder.py
pymc_experimental/inference/smc/__init__.py
pymc_experimental/inference/smc/sampling.py
pymc_experimental/model/__init__.py
pymc_experimental/model/model_api.py
pymc_experimental/model/marginal/__init__.py
pymc_experimental/model/marginal/distributions.py
pymc_experimental/model/marginal/graph_analysis.py
pymc_experimental/model/marginal/marginal_model.py
pymc_experimental/model/transforms/__init__.py
pymc_experimental/model/transforms/autoreparam.py
pymc_experimental/preprocessing/__init__.py
pymc_experimental/preprocessing/standard_scaler.py
pymc_experimental/statespace/__init__.py
pymc_experimental/statespace/core/__init__.py
pymc_experimental/statespace/core/compile.py
pymc_experimental/statespace/core/representation.py
pymc_experimental/statespace/core/statespace.py
pymc_experimental/statespace/filters/__init__.py
pymc_experimental/statespace/filters/distributions.py
pymc_experimental/statespace/filters/kalman_filter.py
pymc_experimental/statespace/filters/kalman_smoother.py
pymc_experimental/statespace/filters/utilities.py
pymc_experimental/statespace/models/ETS.py
pymc_experimental/statespace/models/SARIMAX.py
pymc_experimental/statespace/models/VARMAX.py
pymc_experimental-0.1.4.dist-info/LICENSE
pymc_experimental-0.1.4.dist-info/METADATA
pymc_experimental-0.1.4.dist-info/WHEEL
pymc_experimental-0.1.4.dist-info/top_level.txt
pymc_experimental-0.1.4.dist-info/RECORD
