Metadata-Version: 2.1
Name: pymc-experimental
Version: 0.1.4
Summary: A home for new additions to PyMC, which may include unusual probability distribitions, advanced model fitting algorithms, or any code that may be inappropriate to include in the pymc repository, but may want to be made available to users.
Home-page: http://github.com/pymc-devs/pymc-experimental
Maintainer: PyMC Developers
Maintainer-email: pymc.devs@gmail.com
License: Apache License, Version 2.0
Classifier: Development Status :: 5 - Production/Stable
Classifier: Programming Language :: Python
Classifier: Programming Language :: Python :: 3
Classifier: Programming Language :: Python :: 3.10
Classifier: Programming Language :: Python :: 3.11
Classifier: Programming Language :: Python :: 3.12
Classifier: License :: OSI Approved :: Apache Software License
Classifier: Intended Audience :: Science/Research
Classifier: Topic :: Scientific/Engineering
Classifier: Topic :: Scientific/Engineering :: Mathematics
Classifier: Operating System :: OS Independent
Requires-Python: >=3.10
License-File: LICENSE
Requires-Dist: pymc>=5.19.1
Requires-Dist: scikit-learn
Provides-Extra: dask-histogram
Requires-Dist: dask[complete]; extra == "dask-histogram"
Requires-Dist: xhistogram; extra == "dask-histogram"
Provides-Extra: histogram
Requires-Dist: xhistogram; extra == "histogram"
Provides-Extra: complete
Requires-Dist: dask[complete]; extra == "complete"
Requires-Dist: xhistogram; extra == "complete"
Provides-Extra: dev
Requires-Dist: dask[all]; extra == "dev"
Requires-Dist: blackjax; extra == "dev"
Requires-Dist: statsmodels; extra == "dev"
